adaseq/__init__.py
adaseq/main.py
adaseq/metainfo.py
adaseq/ms_patch.py
adaseq/version.py
adaseq/commands/__init__.py
adaseq/commands/pretrain.py
adaseq/commands/subcommand.py
adaseq/commands/test.py
adaseq/commands/train.py
adaseq/data/__init__.py
adaseq/data/batch.py
adaseq/data/constant.py
adaseq/data/dataset_manager.py
adaseq/data/span_utils.py
adaseq/data/tokenizer.py
adaseq/data/utils.py
adaseq/data/data_collators/__init__.py
adaseq/data/data_collators/base.py
adaseq/data/data_collators/multilabel_typing_data_collator_with_padding.py
adaseq/data/data_collators/pretraining_data_collator_with_padding.py
adaseq/data/data_collators/sequence_labeling_data_collator_with_padding.py
adaseq/data/data_collators/span_extraction_data_collator_with_padding.py
adaseq/data/data_collators/twostage_data_collator_with_padding.py
adaseq/data/data_collators/word_extraction_data_collator_with_padding.py
adaseq/data/dataset_builders/__init__.py
adaseq/data/dataset_builders/base.py
adaseq/data/dataset_builders/entity_typing_dataset_builder.py
adaseq/data/dataset_builders/mcce_entity_typing_dataset_builder.py
adaseq/data/dataset_builders/named_entity_recognition_dataset_builder.py
adaseq/data/dataset_builders/relation_extraction_dataset_builder.py
adaseq/data/dataset_dumpers/__init__.py
adaseq/data/dataset_dumpers/base.py
adaseq/data/dataset_dumpers/named_entity_recognition_dataset_dumper.py
adaseq/data/preprocessors/__init__.py
adaseq/data/preprocessors/multilabel_typing_preprocessor.py
adaseq/data/preprocessors/nlp_preprocessor.py
adaseq/data/preprocessors/pretraining_preprocessor.py
adaseq/data/preprocessors/relation_extraction_preprocessor.py
adaseq/data/preprocessors/sequence_labeling_preprocessor.py
adaseq/data/preprocessors/span_extraction_preprocessor.py
adaseq/data/preprocessors/twostage_preprocessor.py
adaseq/data/preprocessors/word_extraction_preprocessor.py
adaseq/exporters/__init__.py
adaseq/exporters/base.py
adaseq/exporters/multilabel_typing_model_exporter.py
adaseq-0.6.6.dist-info/LICENSE
adaseq-0.6.6.dist-info/METADATA
adaseq-0.6.6.dist-info/WHEEL
adaseq-0.6.6.dist-info/entry_points.txt
adaseq-0.6.6.dist-info/top_level.txt
adaseq-0.6.6.dist-info/RECORD
