Metadata-Version: 2.1
Name: adaseq
Version: 0.6.6
Summary: AdaSeq: An All-in-One Library for Developing State-of-the-Art Sequence Understanding Models
Home-page: https://github.com/modelscope/adaseq
Author: Alibaba Damo Academy NLP foundation team
License: Apache License 2.0
Platform: any
Requires-Python: >=3.7.0
License-File: LICENSE
Requires-Dist: addict
Requires-Dist: datasets
Requires-Dist: modelscope (>=1.4.0)
Requires-Dist: seqeval
Requires-Dist: torch (>=1.11.0)
Requires-Dist: tqdm (>=4.64.0)
Requires-Dist: transformers (>=4.21.0)
Requires-Dist: urllib3 (>=1.26.0)
